bgp/__init__.py
bgp/bgp_test.py
bgp/config.py
bgp/utils.py
bgp/modules/__init__.py
bgp/modules/terms.py
obgp-0.0.42.dist-info/METADATA
obgp-0.0.42.dist-info/WHEEL
obgp-0.0.42.dist-info/top_level.txt
obgp-0.0.42.dist-info/RECORD
