Metadata-Version: 2.1
Name: obgp
Version: 0.0.42
Summary: Open Book Genome Project
Home-page: https://github.com/Open-Book-Genome-Project/sequencer
Author: OBGP
Author-email: michael.karpeles@gmail.com
License: https://www.gnu.org/licenses/agpl-3.0.en.html
Keywords: open book genome fulltext analysis
Platform: any
Classifier: License :: OSI Approved :: GNU Affero General Public License v3 or later (AGPLv3+)
Requires-Dist: beautifulsoup4 (==4.9.0)
Requires-Dist: internetarchive (==3.0.0)
Requires-Dist: lxml (==4.6.5)
Requires-Dist: configparser (==4.0.2)
Requires-Dist: textstat (==0.5.7)
Requires-Dist: py-readability-metrics (==1.4.5)
Requires-Dist: isbnlib (==3.10.7)
Requires-Dist: nltk (==3.7)
